xiaoapi/__init__.py
xiaoapi/admin.py
xiaoapi/conf/__init__.py
xiaoapi/conf/global_settings.py
xiaoapi/conf/module_template/__init__.py
xiaoapi/conf/module_template/crud.py
xiaoapi/conf/module_template/dependencies.py
xiaoapi/conf/module_template/models.py
xiaoapi/conf/module_template/routes.py
xiaoapi/conf/module_template/schemas.py
xiaoapi/conf/project_template/manage.py
xiaoapi/conf/project_template/application/__init__.py
xiaoapi/conf/project_template/application/routes.py
xiaoapi/conf/project_template/application/settings.py
xiaoapi/core/__init__.py
xiaoapi/core/docs.py
xiaoapi/core/event.py
xiaoapi/core/exception.py
xiaoapi/core/fastapi.py
xiaoapi/core/logger.py
xiaoapi/core/middleware.py
xiaoapi/core/mounting.py
xiaoapi/core/router.py
xiaoapi/core/utils.py
xiaoapi/management/__init__.py
xiaoapi/management/commands/__init__.py
xiaoapi/management/commands/createmodule.py
xiaoapi/management/commands/createproject.py
xiaoapi/management/commands/runserver.py
xiaoapi/middleware/__init__.py
xiaoapi/middleware/request_log_middleware.py
xiaoapi/response/__init__.py
xiaoapi/response/response.py
xiaoapi/response/status.py
xiaoapi/static/redoc_ui/redoc.standalone.js
xiaoapi/static/swagger_ui/swagger-ui-bundle.js
xiaoapi/static/swagger_ui/swagger-ui-bundle.js.map
xiaoapi/static/swagger_ui/swagger-ui.css
xiaoapi/static/swagger_ui/swagger-ui.css.map
xiaoapi-0.0.4.dist-info/LICENSE
xiaoapi-0.0.4.dist-info/METADATA
xiaoapi-0.0.4.dist-info/WHEEL
xiaoapi-0.0.4.dist-info/top_level.txt
xiaoapi-0.0.4.dist-info/RECORD
