Metadata-Version: 2.1
Name: xiaoapi
Version: 0.0.4
Summary: A fastapi framework for web development
Author-email: xiaojinli <553555614@qq.com>
License: MIT
Project-URL: Documentation, https://github.com/xiaojinlii/xiaoapi/blob/main/README.md
Project-URL: Source, https://github.com/xiaojinlii/xiaoapi
Keywords: xiaoapi,fastapi,web-framework
Classifier: Framework :: FastAPI
Classifier: Programming Language :: Python :: 3
Requires-Python: >=3.8
License-File: LICENSE
Requires-Dist: fastapi ==0.110.0
Requires-Dist: uvicorn ==0.25.0
Requires-Dist: typer[all] ==0.10.0
Requires-Dist: loguru ==0.7.2
Requires-Dist: orjson ==3.9.15
Requires-Dist: SQLAlchemy ==2.0.25
Requires-Dist: aiosqlite ==0.20.0
Requires-Dist: asyncmy ==0.2.9
